LICENSE
cumulio/__init__.py
cumulio/cumulio.py
cumulio-0.2.5.dist-info/entry_points.txt
cumulio-0.2.5.dist-info/METADATA
cumulio-0.2.5.dist-info/LICENSE
cumulio-0.2.5.dist-info/WHEEL
cumulio-0.2.5.dist-info/RECORD
